[
  {
    "id": 1,
    "text": "Вы обычный студент,у вас всё хорошо вы учитесь на програмиста,вы живёте с мамой так как нету денег купить своё жильё\nНо вы оказуетесь в эру постание машин\nСобытие которые сейчас будут происходить 5 лет спустя\n\nЖанры:апокалипсис,романтика,фантастика\n",
    "answers": [
      {
        "id": 2,
        "text": "[Начать квест]"
      }
    ]
  },
  {
    "id": 2,
    "text": "—Эй ну что долго на ещё идти. Очень злосно сказал Джек\n—нет успокойся пожалуйста. Ответил Майк\nДжек фыркнул и вы продолжили путь.\nСолнце грело,в некоторых местах пели птички.\nНо ваш взгляд часто перебивало лицо одной прекрасной девушки по имени Лиза\n—Всё привал. Сказал Майк",
    "answers": [
      {
        "id": 3,
        "text": "[Положить рюкзак]"
      }
    ]
  },
  {
    "id": 3,
    "text": "Майк присел возле небольшого дерева и задумалсч своём\nИнтересно каким будет мир после восстание(подумал Майк)",
    "answers": [
      {
        "id": 4,
        "text": "[Остаться одному]"
      },
      {
        "id": 5,
        "text": "[Подойти к Лизе]"
      },
      {
        "id": 6,
        "text": "[Подойти к Джеку]"
      },
      {
        "id": 11,
        "text": "[Идти дальше]"
      }
    ]
  },
  {
    "id": 4,
    "text": "Майк всётаки решил их в 2 не трогать Лиза читала книгу а Джек смотрел на карту и думал куда же пойти",
    "answers": [
      {
        "id": 3,
        "text": "-----назад"
      }
    ]
  },
  {
    "id": 5,
    "text": "Майк медленно подошол к Лизе \n—Привет Лиз. Сказал Майк-можно рядом присесть?\n—Да конечно присаживайся.-сказала Лиза \n",
    "answers": [
      {
        "id": 7,
        "text": "[Поговорить о прошлом]"
      }
    ]
  },
  {
    "id": 6,
    "text": "Майл подошёл к Джеку",
    "answers": [
      {
        "id": 8,
        "text": "[Поговорить о карте]"
      }
    ]
  },
  {
    "id": 7,
    "text": "—Эх...ты бы уже щас заканчивала свой мед колидж. Сказал Майк смотря в сторону пустого города Чикаго\n—Ну  да а ты бы уже на работу ходил-с улыбкой сказала Лиза\n—Что есть то есть-сказал Майк",
    "answers": [
      {
        "id": 3,
        "text": "[Отойти от нее]"
      }
    ]
  },
  {
    "id": 8,
    "text": "—Что там по карте. Спросил Майк\n—А тебе то что с этого. Злосно сказал Джейк\n—Ну как бы я тоже жить хочю так как и ты. Возмущонно сказал Майк\n—Хм...Ну ладно скажу тебе.По прямой город.В левой стороне село.В правой поле",
    "answers": [
      {
        "id": 3,
        "text": "[Отойти от него]"
      }
    ]
  },
  {
    "id": 9,
    "text": "Ну вот вы отдохнули подкрепились пора выдвигатьтя в путь",
    "answers": [
      {
        "id": 10,
        "text": "["
      }
    ]
  },
  {
    "id": 10,
    "text": "вы шли долго",
    "answers": [
      {
        "id": 14,
        "text": "[Идти дальше]\n"
      }
    ]
  },
  {
    "id": 11,
    "text": "Вы шли по шоссе и увидили развилку по карте вам надо было направо(карта вела к заброшеной деревне где живут родители Лизы)",
    "answers": [
      {
        "id": 12,
        "text": "[Пойти направо]"
      }
    ]
  },
  {
    "id": 12,
    "text": "Вы шли около 2 часов,все устали, хотели есть \nИ наконец-то вы дошли\n—О боги .закричал Джек\n—Та не ори ты а то вдруг ещё какой-то робот выскочит-сказала Лиза с серьйозным лицом\nДома были все насквось гнилые(имеется введу гнилые доски)но был один хороший на то время дом ",
    "answers": [
      {
        "id": 13,
        "text": "[Войти в дом]"
      }
    ]
  },
  {
    "id": 13,
    "text": "Вы вошли в дом\n—Доча наконец-то ты явилась.Радостно крикнула мама Лизы и обняла её\n—А это кто. Спросил отец Лизы\n—А это...это мои друзья они мне помогают.Сказала Лиза\n—Ну ладно...А вы здесь надолго.Сказала мама Лизы \n—Та не...-Лизу перебили\n—Завтра утром выдвинимся в путь.Сказал Майк\nВам показали комнату\n",
    "answers": [
      {
        "id": 15,
        "text": "[Войти в комнату]"
      }
    ]
  },
  {
    "id": 14,
    "text": "",
    "answers": []
  },
  {
    "id": 15,
    "text": "Вы вошли в комнату...поужинали холодными консервами и лягли спать ",
    "answers": [
      {
        "id": 16,
        "text": "[Лечь спать]"
      }
    ]
  },
  {
    "id": 16,
    "text": "8:00 вы проснулись",
    "answers": [
      {
        "id": 17,
        "text": "[Спуститься на 1 этаж]"
      }
    ]
  },
  {
    "id": 17,
    "text": "Вы спустились\n",
    "answers": [
      {
        "id": 18,
        "text": "[Увидить самолёт роботов]"
      }
    ]
  },
  {
    "id": 18,
    "text": "—Вот те на.Сказал отец Лизы\n—Это же...Это.Вы замерли на месте\n—Та не тупи ты Майк нам надо пробраться туда чтобы Лиза взломала этих роботов\n—Во во во потише чего я сразу.Сказала Лиза-я же на медика ишла\nДжек замолчал\n—я програмист я пойду.Спокойно ответил Майк\n—Ладно иди ты.недовольно сказал Джек\n",
    "answers": [
      {
        "id": 19,
        "text": "[Выйти из дома]"
      }
    ]
  },
  {
    "id": 19,
    "text": "Вы вышли из дома",
    "answers": [
      {
        "id": 20,
        "text": "[Подойти к самолёт]"
      }
    ]
  },
  {
    "id": 20,
    "text": "Вы подошли к самолёту но с него выходит пару роботов ",
    "answers": [
      {
        "id": 21,
        "text": "[Спрятаться за крылом самолёта]"
      }
    ]
  },
  {
    "id": 21,
    "text": "—Ну и что дальше.злосно сказал Майк \n—Я щас отвелаю этих 2х тостеров а вы с Лизой входите во внутрь.Объяснил вам план Джейк\n—Ладно.Сказала Лиза\n",
    "answers": [
      {
        "id": 22,
        "text": "[Ждать пока Джейк отвлечёт роботов]"
      },
      {
        "id": 23,
        "text": "[Не ждать пока он отвлечёт их]"
      }
    ]
  },
  {
    "id": 22,
    "text": "Эй твари металичиские за мной!!!Крикнул Джейк\nОн побежал но...его хватило не на долго",
    "answers": [
      {
        "id": 25,
        "text": "[Вбежать в самолёт]"
      }
    ]
  },
  {
    "id": 23,
    "text": "Вы выскочили из под крыло и в вас полетел\nшквал пуль\n\n",
    "answers": [
      {
        "id": 1,
        "text": "[Конец]"
      }
    ]
  },
  {
    "id": 24,
    "text": "",
    "answers": []
  },
  {
    "id": 25,
    "text": "Вы вбежали в самолёт но когда вы вошли в самолёт вы зарятались и сказали Лизе\n—если у нас что-то не получиться то знай я..я тебя люблю\n—я тебя тоже.Радостно сказала Лиза и вы поцеловались как в последний раз\n—ну всё пора впуть сказал Майк",
    "answers": [
      {
        "id": 26,
        "text": "[Выйти в коридор]"
      }
    ]
  },
  {
    "id": 26,
    "text": "Вы вышли в коридор и увидили главный центр",
    "answers": [
      {
        "id": 27,
        "text": "[Войти в гл.комп.центр]"
      }
    ]
  },
  {
    "id": 27,
    "text": "Вы вошли и увидили компьютер вы подключились к нему но стоял пароль эти твари придумали пароль?(подумал Майк(вы))\n\nУ вас выбор как обойти пароль\n",
    "answers": [
      {
        "id": 28,
        "text": "[Ввести рандом]"
      },
      {
        "id": 29,
        "text": "[Взламывать когбу-то вы хакер]"
      }
    ]
  },
  {
    "id": 28,
    "text": "—Так какой пароль.Сказали вы шопотом\n—попробуй Marmok.Сказала Лиза\n—Ютубера.Удивлённо сказал Майк\n—Ну да быстрей они уже идут!!!сказала Лиза",
    "answers": [
      {
        "id": 31,
        "text": "[Ввести пароль Marmok]"
      }
    ]
  },
  {
    "id": 29,
    "text": "Вы слишком долго взламывали поэтому вас к сажелению убили",
    "answers": [
      {
        "id": 1,
        "text": "[Конец]!1"
      }
    ]
  },
  {
    "id": 30,
    "text": "",
    "answers": []
  },
  {
    "id": 31,
    "text": "Вы даже не ожидали что пароль подойдёт\n—чего прости меня КАК?!!сказал майк удивлённо\n—женская интуиция тебе не понять.с ухмылкой сказала Лиза",
    "answers": [
      {
        "id": 32,
        "text": "[Выключить роботов а затем удалить данные с компьютера]"
      }
    ]
  },
  {
    "id": 32,
    "text": "—Ура да yes мы смогли это-сказал Майк\n—мы...мы живы.щасливо сказала Лиза\n—мы с тобой хоть и не умерли но знай те слова про любовь были не шутка.сказал Майк\n—мои тоже.Радостно ответила Лиза",
    "answers": [
      {
        "id": 33,
        "text": "[5 лет спустя]"
      }
    ]
  },
  {
    "id": 33,
    "text": "Когда весь этот ад закончился вы с Лизой начали встречаться затем вы здели предложение Лизе у вас родилось пару детей которых вы назвали Джейк(в честь Джейка без которого этот план бы не удался)А девочку в честь Лизы \n\nХэппи Энд",
    "answers": [
      {
        "id": 1,
        "text": "[Конец]"
      }
    ]
  },
  {
    "id": 34,
    "text": "",
    "answers": []
  },
  {
    "id": 35,
    "text": "",
    "answers": []
  }
]